simplify/__init__.py
simplify/constants.py
simplify/domain.py
simplifycommerce_sdk_python-1.8.0.dist-info/LICENSE.txt
simplifycommerce_sdk_python-1.8.0.dist-info/METADATA
simplifycommerce_sdk_python-1.8.0.dist-info/WHEEL
simplifycommerce_sdk_python-1.8.0.dist-info/top_level.txt
simplifycommerce_sdk_python-1.8.0.dist-info/RECORD
