Metadata-Version: 2.1
Name: simplifycommerce-sdk-python
Version: 1.8.0
Summary: Simplify Commerce Python SDK
Home-page: https://www.simplify.com/commerce
Author: Simplify Commerce
Author-email: support@simplify.com
License: BSD
Classifier: License :: OSI Approved :: BSD License
License-File: LICENSE.txt
